mutwo/ekmelily_converters/__init__.py
mutwo/ekmelily_converters/configurations.py
mutwo/ekmelily_converters/constants.py
mutwo/ekmelily_converters/ekmelily.py
mutwo.ext_ekmelily-0.6.2.dist-info/LICENSE
mutwo.ext_ekmelily-0.6.2.dist-info/METADATA
mutwo.ext_ekmelily-0.6.2.dist-info/WHEEL
mutwo.ext_ekmelily-0.6.2.dist-info/top_level.txt
mutwo.ext_ekmelily-0.6.2.dist-info/RECORD
