Metadata-Version: 2.1
Name: mutwo.ext-ekmelily
Version: 0.6.2
Summary: ekmelily extension for event based framework for generative art
Home-page: https://github.com/mutwo-org/mutwo.ext-ekmelily
Author: Levin Eric Zimmermann
Author-email: levin.eric.zimmermann@posteo.eu
License: GPL
Project-URL: Documentation, https://mutwo.readthedocs.io/en/latest/
Platform: UNKNOWN
Requires-Python: >=3.9, <4
License-File: LICENSE
Requires-Dist: mutwo.ext-core (<0.60.0,>=0.59.0)
Requires-Dist: mutwo.ext-music (<0.17.0,>=0.14.0)
Provides-Extra: testing
Requires-Dist: nose ; extra == 'testing'
Requires-Dist: coveralls ; extra == 'testing'
